pricedisplay/__init__.py
pricedisplay/__main__.py
pricedisplay/application.py
pricedisplay/config.migrate
pricedisplay/config.template
pricedisplay/configparser.py
pricedisplay/datahandler.py
pricedisplay/exceptions.py
pricedisplay/graphics.py
pricedisplay-0.7.1.dist-info/LICENSE.md
pricedisplay-0.7.1.dist-info/METADATA
pricedisplay-0.7.1.dist-info/WHEEL
pricedisplay-0.7.1.dist-info/entry_points.txt
pricedisplay-0.7.1.dist-info/RECORD
