Metadata-Version: 2.1
Name: pricedisplay
Version: 0.7.1
Summary: Terminal display for the Finnish power price.
Home-page: https://github.com/YukiNeko-hime/pricedisplay
License: LICENSE.md
Author: Lumi
Requires-Python: >=3.9,<4.0
Classifier: License :: OSI Approved :: GNU General Public License v3 (GPLv3)
Classifier: License :: Other/Proprietary License
Classifier: Operating System :: OS Independent
Classifier: Programming Language :: Python :: 3
Classifier: Programming Language :: Python :: 3.9
Classifier: Programming Language :: Python :: 3.10
Classifier: Programming Language :: Python :: 3.11
Requires-Dist: argparse (>=1.4.0,<2.0.0)
Requires-Dist: datetime (>=5.2,<6.0)
Requires-Dist: pyyaml (>=6.0.1,<7.0.0)
Requires-Dist: requests (>=2.31.0,<3.0.0)
Requires-Dist: sparklines (>=0.4.2,<0.5.0)
Requires-Dist: usersettings (>=1.1.5,<2.0.0)
Requires-Dist: windows-curses (>=2.3.1,<3.0.0) ; sys_platform == "win32"
Project-URL: Repository, https://github.com/YukiNeko-hime/pricedisplay
